blockdiag/__init__.py
blockdiag/builder.py
blockdiag/command.py
blockdiag/drawer.py
blockdiag/elements.py
blockdiag/metrics.py
blockdiag/parser.py
blockdiag/imagedraw/__init__.py
blockdiag/imagedraw/base.py
blockdiag/imagedraw/pdf.py
blockdiag/imagedraw/png.py
blockdiag/imagedraw/simplesvg.py
blockdiag/imagedraw/svg.py
blockdiag/imagedraw/textfolder.py
blockdiag/imagedraw/filters/__init__.py
blockdiag/imagedraw/filters/linejump.py
blockdiag/imagedraw/utils/__init__.py
blockdiag/imagedraw/utils/ellipse.py
blockdiag/noderenderer/__init__.py
blockdiag/noderenderer/actor.py
blockdiag/noderenderer/base.py
blockdiag/noderenderer/beginpoint.py
blockdiag/noderenderer/box.py
blockdiag/noderenderer/circle.py
blockdiag/noderenderer/cloud.py
blockdiag/noderenderer/diamond.py
blockdiag/noderenderer/dots.py
blockdiag/noderenderer/ellipse.py
blockdiag/noderenderer/endpoint.py
blockdiag/noderenderer/mail.py
blockdiag/noderenderer/minidiamond.py
blockdiag/noderenderer/none.py
blockdiag/noderenderer/note.py
blockdiag/noderenderer/roundedbox.py
blockdiag/noderenderer/square.py
blockdiag/noderenderer/textbox.py
blockdiag/noderenderer/flowchart/__init__.py
blockdiag/noderenderer/flowchart/database.py
blockdiag/noderenderer/flowchart/input.py
blockdiag/noderenderer/flowchart/loopin.py
blockdiag/noderenderer/flowchart/loopout.py
blockdiag/noderenderer/flowchart/terminator.py
blockdiag/plugins/__init__.py
blockdiag/plugins/attributes.py
blockdiag/plugins/autoclass.py
blockdiag/tests/__init__.py
blockdiag/tests/test_boot_params.py
blockdiag/tests/test_builder.py
blockdiag/tests/test_builder_edge.py
blockdiag/tests/test_builder_errors.py
blockdiag/tests/test_builder_group.py
blockdiag/tests/test_builder_node.py
blockdiag/tests/test_builder_separate.py
blockdiag/tests/test_command.py
blockdiag/tests/test_generate_diagram.py
blockdiag/tests/test_imagedraw_textfolder.py
blockdiag/tests/test_imagedraw_utils.py
blockdiag/tests/test_parser.py
blockdiag/tests/test_utils.py
blockdiag-3.0.0.dist-info/LICENSE
blockdiag-3.0.0.dist-info/METADATA
blockdiag-3.0.0.dist-info/WHEEL
blockdiag-3.0.0.dist-info/entry_points.txt
blockdiag-3.0.0.dist-info/top_level.txt
blockdiag-3.0.0.dist-info/RECORD
