Metadata-Version: 2.1
Name: blockdiag
Version: 3.0.0
Summary: blockdiag generates block-diagram image from text
Home-page: http://blockdiag.com/
Author: Takeshi Komiya
Author-email: i.tkomiya@gmail.com
License: Apache License 2.0
Download-URL: http://pypi.python.org/pypi/blockdiag
Project-URL: Code, https://github.com/blockdiag/blockdiag
Project-URL: Issue tracker, https://github.com/blockdiag/blockdiag/issues
Keywords: diagram,generator
Platform: UNKNOWN
Classifier: Development Status :: 5 - Production/Stable
Classifier: Intended Audience :: System Administrators
Classifier: License :: OSI Approved :: Apache Software License
Classifier: Programming Language :: Python
Classifier: Programming Language :: Python :: 3.7
Classifier: Programming Language :: Python :: 3.8
Classifier: Programming Language :: Python :: 3.9
Classifier: Topic :: Software Development
Classifier: Topic :: Software Development :: Documentation
Classifier: Topic :: Text Processing :: Markup
Requires-Python: >=3.7
Provides-Extra: pdf
Provides-Extra: rst
Provides-Extra: testing
License-File: LICENSE
